{
    "data": [
        {
            "id": 1,
            "pie": -0.031,
            "pace": 98.08,
            "assist_percentage": 0.15,
            "assist_ratio": 25,
            "assist_to_turnover": 0.75,
            "defensive_rating": 100,
            "defensive_rebound_percentage": 0.132,
            "effective_field_goal_percentage": 0,
            "net_rating": -20,
            "offensive_rating": 80,
            "offensive_rebound_percentage": 0.069,
            "rebound_percentage": 0.104,
            "true_shooting_percentage": 0.087,
            "turnover_ratio": 33.3,
            "usage_percentage": 0.127,
            "player": {
                "id": 2970,
                "first_name": "Olden",
                "last_name": "Polynice",
                "position": "",
                "height": "7-0",
                "weight": "250",
                "jersey_number": "0",
                "college": "Virginia",
                "country": "USA",
                "draft_year": 1987,
                "draft_round": 1,
                "draft_number": 8,
                "team_id": 26
            },
            "team": {
                "id": 26,
                "conference": "West",
                "division": "Pacific",
                "city": "Sacramento",
                "name": "Kings",
                "full_name": "Sacramento Kings",
                "abbreviation": "SAC"
            },
            "game": {
                "id": 3524,
                "date": "1996-11-01",
                "season": 1996,
                "status": "Final",
                "period": 4,
                "time": " ",
                "postseason": false,
                "home_team_score": 96,
                "visitor_team_score": 85,
                "home_team_id": 11,
                "visitor_team_id": 26
            }
        },
        {
            "id": 2,
            "pie": 0.094,
            "pace": 95.8,
            "assist_percentage": 0.19,
            "assist_ratio": 21.1,
            "assist_to_turnover": 1,
            "defensive_rating": 100,
            "defensive_rebound_percentage": 0.065,
            "effective_field_goal_percentage": 0.636,
            "net_rating": -1.4,
            "offensive_rating": 98.6,
            "offensive_rebound_percentage": 0.037,
            "rebound_percentage": 0.055,
            "true_shooting_percentage": 0.636,
            "turnover_ratio": 21.1,
            "usage_percentage": 0.179,
            "player": {
                "id": 990,
                "first_name": "Corliss",
                "last_name": "Williamson",
                "position": "",
                "height": "6-7",
                "weight": "245",
                "jersey_number": "34",
                "college": "Arkansas",
                "country": "USA",
                "draft_year": 1995,
                "draft_round": 1,
                "draft_number": 13,
                "team_id": 26
            },
            "team": {
                "id": 26,
                "conference": "West",
                "division": "Pacific",
                "city": "Sacramento",
                "name": "Kings",
                "full_name": "Sacramento Kings",
                "abbreviation": "SAC"
            },
            "game": {
                "id": 3524,
                "date": "1996-11-01",
                "season": 1996,
                "status": "Final",
                "period": 4,
                "time": " ",
                "postseason": false,
                "home_team_score": 96,
                "visitor_team_score": 85,
                "home_team_id": 11,
                "visitor_team_id": 26
            }
        },
        {
            "id": 3,
            "pie": 0.065,
            "pace": 98.03,
            "assist_percentage": 0,
            "assist_ratio": 0,
            "assist_to_turnover": 0,
            "defensive_rating": 82.4,
            "defensive_rebound_percentage": 0.152,
            "effective_field_goal_percentage": 0.273,
            "net_rating": -15,
            "offensive_rating": 67.3,
            "offensive_rebound_percentage": 0.04,
            "rebound_percentage": 0.103,
            "true_shooting_percentage": 0.337,
            "turnover_ratio": 7.7,
            "usage_percentage": 0.224,
            "player": {
                "id": 892,
                "first_name": "Brian",
                "last_name": "Grant",
                "position": "",
                "height": "6-9",
                "weight": "254",
                "jersey_number": "55",
                "college": "Xavier",
                "country": "USA",
                "draft_year": 1994,
                "draft_round": 1,
                "draft_number": 8,
                "team_id": 16
            },
            "team": {
                "id": 26,
                "conference": "West",
                "division": "Pacific",
                "city": "Sacramento",
                "name": "Kings",
                "full_name": "Sacramento Kings",
                "abbreviation": "SAC"
            },
            "game": {
                "id": 3524,
                "date": "1996-11-01",
                "season": 1996,
                "status": "Final",
                "period": 4,
                "time": " ",
                "postseason": false,
                "home_team_score": 96,
                "visitor_team_score": 85,
                "home_team_id": 11,
                "visitor_team_id": 26
            }
        },
        {
            "id": 4,
            "pie": 0.156,
            "pace": 98.08,
            "assist_percentage": 0.25,
            "assist_ratio": 16.7,
            "assist_to_turnover": 1,
            "defensive_rating": 100,
            "defensive_rebound_percentage": 0.139,
            "effective_field_goal_percentage": 0.542,
            "net_rating": -27.7,
            "offensive_rating": 72.3,
            "offensive_rebound_percentage": 0,
            "rebound_percentage": 0.077,
            "true_shooting_percentage": 0.563,
            "turnover_ratio": 16.7,
            "usage_percentage": 0.211,
            "player": {
                "id": 604,
                "first_name": "Mitch",
                "last_name": "Richmond",
                "position": "",
                "height": "6-5",
                "weight": "220",
                "jersey_number": "2",
                "college": "Kansas State",
                "country": "USA",
                "draft_year": 1988,
                "draft_round": 1,
                "draft_number": 5,
                "team_id": 26
            },
            "team": {
                "id": 26,
                "conference": "West",
                "division": "Pacific",
                "city": "Sacramento",
                "name": "Kings",
                "full_name": "Sacramento Kings",
                "abbreviation": "SAC"
            },
            "game": {
                "id": 3524,
                "date": "1996-11-01",
                "season": 1996,
                "status": "Final",
                "period": 4,
                "time": " ",
                "postseason": false,
                "home_team_score": 96,
                "visitor_team_score": 85,
                "home_team_id": 11,
                "visitor_team_id": 26
            }
        },
        {
            "id": 5,
            "pie": 0.169,
            "pace": 94.53,
            "assist_percentage": 0.385,
            "assist_ratio": 23.8,
            "assist_to_turnover": 2.5,
            "defensive_rating": 96.6,
            "defensive_rebound_percentage": 0.056,
            "effective_field_goal_percentage": 0.577,
            "net_rating": -12.1,
            "offensive_rating": 84.5,
            "offensive_rebound_percentage": 0,
            "rebound_percentage": 0.032,
            "true_shooting_percentage": 0.612,
            "turnover_ratio": 9.5,
            "usage_percentage": 0.25,
            "player": {
                "id": 3023,
                "first_name": "Mahmoud",
                "last_name": "Abdul-Rauf",
                "position": "",
                "height": "6-1",
                "weight": "162",
                "jersey_number": "1",
                "college": "Louisiana State",
                "country": "USA",
                "draft_year": 1990,
                "draft_round": 1,
                "draft_number": 3,
                "team_id": 8
            },
            "team": {
                "id": 26,
                "conference": "West",
                "division": "Pacific",
                "city": "Sacramento",
                "name": "Kings",
                "full_name": "Sacramento Kings",
                "abbreviation": "SAC"
            },
            "game": {
                "id": 3524,
                "date": "1996-11-01",
                "season": 1996,
                "status": "Final",
                "period": 4,
                "time": " ",
                "postseason": false,
                "home_team_score": 96,
                "visitor_team_score": 85,
                "home_team_id": 11,
                "visitor_team_id": 26
            }
        },
        {
            "id": 6,
            "pie": 0.144,
            "pace": 103.76,
            "assist_percentage": 0.059,
            "assist_ratio": 10,
            "assist_to_turnover": 0.25,
            "defensive_rating": 113.2,
            "defensive_rebound_percentage": 0.296,
            "effective_field_goal_percentage": 0.667,
            "net_rating": -20.6,
            "offensive_rating": 92.6,
            "offensive_rebound_percentage": 0.111,
            "rebound_percentage": 0.222,
            "true_shooting_percentage": 0.84,
            "turnover_ratio": 40,
            "usage_percentage": 0.153,
            "player": {
                "id": 894,
                "first_name": "Michael",
                "last_name": "Smith",
                "position": "",
                "height": "6-8",
                "weight": "240",
                "jersey_number": "34",
                "college": "Providence",
                "country": "USA",
                "draft_year": 1994,
                "draft_round": 2,
                "draft_number": 35,
                "team_id": 26
            },
            "team": {
                "id": 26,
                "conference": "West",
                "division": "Pacific",
                "city": "Sacramento",
                "name": "Kings",
                "full_name": "Sacramento Kings",
                "abbreviation": "SAC"
            },
            "game": {
                "id": 3524,
                "date": "1996-11-01",
                "season": 1996,
                "status": "Final",
                "period": 4,
                "time": " ",
                "postseason": false,
                "home_team_score": 96,
                "visitor_team_score": 85,
                "home_team_id": 11,
                "visitor_team_id": 26
            }
        },
        {
            "id": 7,
            "pie": -0.012,
            "pace": 109.41,
            "assist_percentage": 0.111,
            "assist_ratio": 9.1,
            "assist_to_turnover": 0.25,
            "defensive_rating": 95.1,
            "defensive_rebound_percentage": 0.05,
            "effective_field_goal_percentage": 0.5,
            "net_rating": -21.3,
            "offensive_rating": 73.8,
            "offensive_rebound_percentage": 0.077,
            "rebound_percentage": 0.061,
            "true_shooting_percentage": 0.5,
            "turnover_ratio": 36.4,
            "usage_percentage": 0.213,
            "player": {
                "id": 2919,
                "first_name": "Lionel",
                "last_name": "Simmons",
                "position": "",
                "height": "6-7",
                "weight": "210",
                "jersey_number": "22",
                "college": "La Salle",
                "country": "USA",
                "draft_year": 1990,
                "draft_round": 1,
                "draft_number": 7,
                "team_id": 26
            },
            "team": {
                "id": 26,
                "conference": "West",
                "division": "Pacific",
                "city": "Sacramento",
                "name": "Kings",
                "full_name": "Sacramento Kings",
                "abbreviation": "SAC"
            },
            "game": {
                "id": 3524,
                "date": "1996-11-01",
                "season": 1996,
                "status": "Final",
                "period": 4,
                "time": " ",
                "postseason": false,
                "home_team_score": 96,
                "visitor_team_score": 85,
                "home_team_id": 11,
                "visitor_team_id": 26
            }
        },
        {
            "id": 8,
            "pie": 0.104,
            "pace": 113.02,
            "assist_percentage": 0,
            "assist_ratio": 0,
            "assist_to_turnover": 0,
            "defensive_rating": 80,
            "defensive_rebound_percentage": 0.032,
            "effective_field_goal_percentage": 0.364,
            "net_rating": -5,
            "offensive_rating": 75,
            "offensive_rebound_percentage": 0,
            "rebound_percentage": 0.018,
            "true_shooting_percentage": 0.482,
            "turnover_ratio": 21.1,
            "usage_percentage": 0.288,
            "player": {
                "id": 969,
                "first_name": "Tyus",
                "last_name": "Edney",
                "position": "",
                "height": "5-10",
                "weight": "166",
                "jersey_number": "2",
                "college": "UCLA",
                "country": "USA",
                "draft_year": 1995,
                "draft_round": 2,
                "draft_number": 47,
                "team_id": 26
            },
            "team": {
                "id": 26,
                "conference": "West",
                "division": "Pacific",
                "city": "Sacramento",
                "name": "Kings",
                "full_name": "Sacramento Kings",
                "abbreviation": "SAC"
            },
            "game": {
                "id": 3524,
                "date": "1996-11-01",
                "season": 1996,
                "status": "Final",
                "period": 4,
                "time": " ",
                "postseason": false,
                "home_team_score": 96,
                "visitor_team_score": 85,
                "home_team_id": 11,
                "visitor_team_id": 26
            }
        },
        {
            "id": 9,
            "pie": 0.045,
            "pace": 106.61,
            "assist_percentage": 0.091,
            "assist_ratio": 25,
            "assist_to_turnover": 1,
            "defensive_rating": 86.5,
            "defensive_rebound_percentage": 0.1,
            "effective_field_goal_percentage": 1,
            "net_rating": 5.2,
            "offensive_rating": 91.7,
            "offensive_rebound_percentage": 0.083,
            "rebound_percentage": 0.094,
            "true_shooting_percentage": 0.798,
            "turnover_ratio": 25,
            "usage_percentage": 0.073,
            "player": {
                "id": 2917,
                "first_name": "Duane",
                "last_name": "Causwell",
                "position": "",
                "height": "7-0",
                "weight": "255",
                "jersey_number": "4",
                "college": "Temple",
                "country": "USA",
                "draft_year": 1990,
                "draft_round": 1,
                "draft_number": 18,
                "team_id": 26
            },
            "team": {
                "id": 26,
                "conference": "West",
                "division": "Pacific",
                "city": "Sacramento",
                "name": "Kings",
                "full_name": "Sacramento Kings",
                "abbreviation": "SAC"
            },
            "game": {
                "id": 3524,
                "date": "1996-11-01",
                "season": 1996,
                "status": "Final",
                "period": 4,
                "time": " ",
                "postseason": false,
                "home_team_score": 96,
                "visitor_team_score": 85,
                "home_team_id": 11,
                "visitor_team_id": 26
            }
        },
        {
            "id": 10,
            "pie": 0.182,
            "pace": 94.96,
            "assist_percentage": 0.176,
            "assist_ratio": 17.6,
            "assist_to_turnover": 0,
            "defensive_rating": 81.3,
            "defensive_rebound_percentage": 0,
            "effective_field_goal_percentage": 0.708,
            "net_rating": 23.4,
            "offensive_rating": 104.7,
            "offensive_rebound_percentage": 0.103,
            "rebound_percentage": 0.06,
            "true_shooting_percentage": 0.727,
            "turnover_ratio": 0,
            "usage_percentage": 0.179,
            "player": {
                "id": 3056,
                "first_name": "Mario",
                "last_name": "Elie",
                "position": "",
                "height": "6-5",
                "weight": "225",
                "jersey_number": "17",
                "college": "American International",
                "country": "USA",
                "draft_year": 1985,
                "draft_round": 7,
                "draft_number": 160,
                "team_id": 11
            },
            "team": {
                "id": 11,
                "conference": "West",
                "division": "Southwest",
                "city": "Houston",
                "name": "Rockets",
                "full_name": "Houston Rockets",
                "abbreviation": "HOU"
            },
            "game": {
                "id": 3524,
                "date": "1996-11-01",
                "season": 1996,
                "status": "Final",
                "period": 4,
                "time": " ",
                "postseason": false,
                "home_team_score": 96,
                "visitor_team_score": 85,
                "home_team_id": 11,
                "visitor_team_id": 26
            }
        },
        {
            "id": 11,
            "pie": -0.018,
            "pace": 101.17,
            "assist_percentage": 0,
            "assist_ratio": 0,
            "assist_to_turnover": 0,
            "defensive_rating": 79,
            "defensive_rebound_percentage": 0.114,
            "effective_field_goal_percentage": 0.25,
            "net_rating": 8.8,
            "offensive_rating": 87.8,
            "offensive_rebound_percentage": 0.021,
            "rebound_percentage": 0.06,
            "true_shooting_percentage": 0.311,
            "turnover_ratio": 13.3,
            "usage_percentage": 0.149,
            "player": {
                "id": 579,
                "first_name": "Kevin",
                "last_name": "Willis",
                "position": "",
                "height": "7-0",
                "weight": "245",
                "jersey_number": "45",
                "college": "Michigan State",
                "country": "USA",
                "draft_year": 1984,
                "draft_round": 1,
                "draft_number": 11,
                "team_id": 1
            },
            "team": {
                "id": 11,
                "conference": "West",
                "division": "Southwest",
                "city": "Houston",
                "name": "Rockets",
                "full_name": "Houston Rockets",
                "abbreviation": "HOU"
            },
            "game": {
                "id": 3524,
                "date": "1996-11-01",
                "season": 1996,
                "status": "Final",
                "period": 4,
                "time": " ",
                "postseason": false,
                "home_team_score": 96,
                "visitor_team_score": 85,
                "home_team_id": 11,
                "visitor_team_id": 26
            }
        },
        {
            "id": 12,
            "pie": 0.198,
            "pace": 98.15,
            "assist_percentage": 0.273,
            "assist_ratio": 21.4,
            "assist_to_turnover": 1.5,
            "defensive_rating": 77.2,
            "defensive_rebound_percentage": 0.286,
            "effective_field_goal_percentage": 0.385,
            "net_rating": 25.3,
            "offensive_rating": 102.5,
            "offensive_rebound_percentage": 0.065,
            "rebound_percentage": 0.16,
            "true_shooting_percentage": 0.489,
            "turnover_ratio": 14.3,
            "usage_percentage": 0.232,
            "player": {
                "id": 540,
                "first_name": "Hakeem",
                "last_name": "Olajuwon",
                "position": "",
                "height": "7-0",
                "weight": "255",
                "jersey_number": "34",
                "college": "Houston",
                "country": "Nigeria",
                "draft_year": 1984,
                "draft_round": 1,
                "draft_number": 1,
                "team_id": 11
            },
            "team": {
                "id": 11,
                "conference": "West",
                "division": "Southwest",
                "city": "Houston",
                "name": "Rockets",
                "full_name": "Houston Rockets",
                "abbreviation": "HOU"
            },
            "game": {
                "id": 3524,
                "date": "1996-11-01",
                "season": 1996,
                "status": "Final",
                "period": 4,
                "time": " ",
                "postseason": false,
                "home_team_score": 96,
                "visitor_team_score": 85,
                "home_team_id": 11,
                "visitor_team_id": 26
            }
        },
        {
            "id": 13,
            "pie": 0.242,
            "pace": 99.15,
            "assist_percentage": 0.409,
            "assist_ratio": 22,
            "assist_to_turnover": 1.29,
            "defensive_rating": 84.1,
            "defensive_rebound_percentage": 0.167,
            "effective_field_goal_percentage": 0.429,
            "net_rating": 13.6,
            "offensive_rating": 97.7,
            "offensive_rebound_percentage": 0.078,
            "rebound_percentage": 0.115,
            "true_shooting_percentage": 0.492,
            "turnover_ratio": 17.1,
            "usage_percentage": 0.296,
            "player": {
                "id": 632,
                "first_name": "Clyde",
                "last_name": "Drexler",
                "position": "",
                "height": "6-7",
                "weight": "222",
                "jersey_number": "22",
                "college": "Houston",
                "country": "USA",
                "draft_year": 1983,
                "draft_round": 1,
                "draft_number": 14,
                "team_id": 25
            },
            "team": {
                "id": 11,
                "conference": "West",
                "division": "Southwest",
                "city": "Houston",
                "name": "Rockets",
                "full_name": "Houston Rockets",
                "abbreviation": "HOU"
            },
            "game": {
                "id": 3524,
                "date": "1996-11-01",
                "season": 1996,
                "status": "Final",
                "period": 4,
                "time": " ",
                "postseason": false,
                "home_team_score": 96,
                "visitor_team_score": 85,
                "home_team_id": 11,
                "visitor_team_id": 26
            }
        },
        {
            "id": 14,
            "pie": 0.037,
            "pace": 96.49,
            "assist_percentage": 0.05,
            "assist_ratio": 9.1,
            "assist_to_turnover": 1,
            "defensive_rating": 84.8,
            "defensive_rebound_percentage": 0.036,
            "effective_field_goal_percentage": 0.438,
            "net_rating": 10.5,
            "offensive_rating": 95.4,
            "offensive_rebound_percentage": 0.023,
            "rebound_percentage": 0.028,
            "true_shooting_percentage": 0.45,
            "turnover_ratio": 9.1,
            "usage_percentage": 0.125,
            "player": {
                "id": 1044,
                "first_name": "Matt",
                "last_name": "Maloney",
                "position": "G",
                "height": "6-3",
                "weight": "200",
                "jersey_number": "12",
                "college": "Pennsylvania",
                "country": "USA",
                "draft_year": null,
                "draft_round": null,
                "draft_number": null,
                "team_id": 11
            },
            "team": {
                "id": 11,
                "conference": "West",
                "division": "Southwest",
                "city": "Houston",
                "name": "Rockets",
                "full_name": "Houston Rockets",
                "abbreviation": "HOU"
            },
            "game": {
                "id": 3524,
                "date": "1996-11-01",
                "season": 1996,
                "status": "Final",
                "period": 4,
                "time": " ",
                "postseason": false,
                "home_team_score": 96,
                "visitor_team_score": 85,
                "home_team_id": 11,
                "visitor_team_id": 26
            }
        },
        {
            "id": 15,
            "pie": 0.13,
            "pace": 107.42,
            "assist_percentage": 0.1,
            "assist_ratio": 11.1,
            "assist_to_turnover": 0.5,
            "defensive_rating": 107.7,
            "defensive_rebound_percentage": 0.273,
            "effective_field_goal_percentage": 0.667,
            "net_rating": -15.2,
            "offensive_rating": 92.5,
            "offensive_rebound_percentage": 0.143,
            "rebound_percentage": 0.188,
            "true_shooting_percentage": 0.667,
            "turnover_ratio": 22.2,
            "usage_percentage": 0.167,
            "player": {
                "id": 1045,
                "first_name": "Othella",
                "last_name": "Harrington",
                "position": "",
                "height": "6-9",
                "weight": "235",
                "jersey_number": "24",
                "college": "Georgetown",
                "country": "USA",
                "draft_year": 1996,
                "draft_round": 2,
                "draft_number": 30,
                "team_id": 20
            },
            "team": {
                "id": 11,
                "conference": "West",
                "division": "Southwest",
                "city": "Houston",
                "name": "Rockets",
                "full_name": "Houston Rockets",
                "abbreviation": "HOU"
            },
            "game": {
                "id": 3524,
                "date": "1996-11-01",
                "season": 1996,
                "status": "Final",
                "period": 4,
                "time": " ",
                "postseason": false,
                "home_team_score": 96,
                "visitor_team_score": 85,
                "home_team_id": 11,
                "visitor_team_id": 26
            }
        },
        {
            "id": 16,
            "pie": -0.154,
            "pace": 103.48,
            "assist_percentage": 0.111,
            "assist_ratio": 20,
            "assist_to_turnover": 0.5,
            "defensive_rating": 76.7,
            "defensive_rebound_percentage": 0.091,
            "effective_field_goal_percentage": 0.5,
            "net_rating": 30.2,
            "offensive_rating": 106.9,
            "offensive_rebound_percentage": 0,
            "rebound_percentage": 0.05,
            "true_shooting_percentage": 0.301,
            "turnover_ratio": 40,
            "usage_percentage": 0.118,
            "player": {
                "id": 1046,
                "first_name": "Randy",
                "last_name": "Livingston",
                "position": "",
                "height": "6-4",
                "weight": "209",
                "jersey_number": "14",
                "college": "Louisiana State",
                "country": "USA",
                "draft_year": 1996,
                "draft_round": 2,
                "draft_number": 42,
                "team_id": 24
            },
            "team": {
                "id": 11,
                "conference": "West",
                "division": "Southwest",
                "city": "Houston",
                "name": "Rockets",
                "full_name": "Houston Rockets",
                "abbreviation": "HOU"
            },
            "game": {
                "id": 3524,
                "date": "1996-11-01",
                "season": 1996,
                "status": "Final",
                "period": 4,
                "time": " ",
                "postseason": false,
                "home_team_score": 96,
                "visitor_team_score": 85,
                "home_team_id": 11,
                "visitor_team_id": 26
            }
        },
        {
            "id": 17,
            "pie": 0.333,
            "pace": 109.14,
            "assist_percentage": 0.333,
            "assist_ratio": 25,
            "assist_to_turnover": 2,
            "defensive_rating": 83.9,
            "defensive_rebound_percentage": 0.182,
            "effective_field_goal_percentage": 0.8,
            "net_rating": 0,
            "offensive_rating": 83.9,
            "offensive_rebound_percentage": 0,
            "rebound_percentage": 0.087,
            "true_shooting_percentage": 0.8,
            "turnover_ratio": 12.5,
            "usage_percentage": 0.162,
            "player": {
                "id": 641,
                "first_name": "Matt",
                "last_name": "Bullard",
                "position": "",
                "height": "6-10",
                "weight": "229",
                "jersey_number": "50",
                "college": "Iowa",
                "country": "USA",
                "draft_year": null,
                "draft_round": null,
                "draft_number": null,
                "team_id": 11
            },
            "team": {
                "id": 11,
                "conference": "West",
                "division": "Southwest",
                "city": "Houston",
                "name": "Rockets",
                "full_name": "Houston Rockets",
                "abbreviation": "HOU"
            },
            "game": {
                "id": 3524,
                "date": "1996-11-01",
                "season": 1996,
                "status": "Final",
                "period": 4,
                "time": " ",
                "postseason": false,
                "home_team_score": 96,
                "visitor_team_score": 85,
                "home_team_id": 11,
                "visitor_team_id": 26
            }
        },
        {
            "id": 18,
            "pie": -0.143,
            "pace": 115.56,
            "assist_percentage": 0.25,
            "assist_ratio": 20,
            "assist_to_turnover": 0.5,
            "defensive_rating": 84.6,
            "defensive_rebound_percentage": 0,
            "effective_field_goal_percentage": 0,
            "net_rating": -7.7,
            "offensive_rating": 76.9,
            "offensive_rebound_percentage": 0.143,
            "rebound_percentage": 0.083,
            "true_shooting_percentage": 0,
            "turnover_ratio": 40,
            "usage_percentage": 0.267,
            "player": {
                "id": 754,
                "first_name": "Sam",
                "last_name": "Mack",
                "position": "",
                "height": "6-7",
                "weight": "220",
                "jersey_number": "7",
                "college": "Houston",
                "country": "USA",
                "draft_year": null,
                "draft_round": null,
                "draft_number": null,
                "team_id": 11
            },
            "team": {
                "id": 11,
                "conference": "West",
                "division": "Southwest",
                "city": "Houston",
                "name": "Rockets",
                "full_name": "Houston Rockets",
                "abbreviation": "HOU"
            },
            "game": {
                "id": 3524,
                "date": "1996-11-01",
                "season": 1996,
                "status": "Final",
                "period": 4,
                "time": " ",
                "postseason": false,
                "home_team_score": 96,
                "visitor_team_score": 85,
                "home_team_id": 11,
                "visitor_team_id": 26
            }
        },
        {
            "id": 19,
            "pie": -0.429,
            "pace": 140.87,
            "assist_percentage": 0.5,
            "assist_ratio": 16.7,
            "assist_to_turnover": 0,
            "defensive_rating": 111.1,
            "defensive_rebound_percentage": 0.333,
            "effective_field_goal_percentage": 0,
            "net_rating": -55.6,
            "offensive_rating": 55.6,
            "offensive_rebound_percentage": 0,
            "rebound_percentage": 0.091,
            "true_shooting_percentage": 0,
            "turnover_ratio": 0,
            "usage_percentage": 0.417,
            "player": {
                "id": 715,
                "first_name": "Tracy",
                "last_name": "Moore",
                "position": "",
                "height": "6-4",
                "weight": "200",
                "jersey_number": "20",
                "college": "Tulsa",
                "country": "USA",
                "draft_year": null,
                "draft_round": null,
                "draft_number": null,
                "team_id": 7
            },
            "team": {
                "id": 11,
                "conference": "West",
                "division": "Southwest",
                "city": "Houston",
                "name": "Rockets",
                "full_name": "Houston Rockets",
                "abbreviation": "HOU"
            },
            "game": {
                "id": 3524,
                "date": "1996-11-01",
                "season": 1996,
                "status": "Final",
                "period": 4,
                "time": " ",
                "postseason": false,
                "home_team_score": 96,
                "visitor_team_score": 85,
                "home_team_id": 11,
                "visitor_team_id": 26
            }
        },
        {
            "id": 20,
            "pie": -1,
            "pace": 180,
            "assist_percentage": 0,
            "assist_ratio": 0,
            "assist_to_turnover": 0,
            "defensive_rating": 100,
            "defensive_rebound_percentage": 0,
            "effective_field_goal_percentage": 0,
            "net_rating": -57.1,
            "offensive_rating": 42.9,
            "offensive_rebound_percentage": 0,
            "rebound_percentage": 0,
            "true_shooting_percentage": 0,
            "turnover_ratio": 0,
            "usage_percentage": 0.111,
            "player": {
                "id": 1047,
                "first_name": "Emanual",
                "last_name": "Davis",
                "position": "",
                "height": "6-5",
                "weight": "195",
                "jersey_number": "15",
                "college": "Delaware State",
                "country": "USA",
                "draft_year": null,
                "draft_round": null,
                "draft_number": null,
                "team_id": 21
            },
            "team": {
                "id": 11,
                "conference": "West",
                "division": "Southwest",
                "city": "Houston",
                "name": "Rockets",
                "full_name": "Houston Rockets",
                "abbreviation": "HOU"
            },
            "game": {
                "id": 3524,
                "date": "1996-11-01",
                "season": 1996,
                "status": "Final",
                "period": 4,
                "time": " ",
                "postseason": false,
                "home_team_score": 96,
                "visitor_team_score": 85,
                "home_team_id": 11,
                "visitor_team_id": 26
            }
        },
        {
            "id": 21,
            "pie": 0,
            "pace": 0,
            "assist_percentage": 0,
            "assist_ratio": 0,
            "assist_to_turnover": 0,
            "defensive_rating": 0,
            "defensive_rebound_percentage": 0,
            "effective_field_goal_percentage": 0,
            "net_rating": 0,
            "offensive_rating": 0,
            "offensive_rebound_percentage": 0,
            "rebound_percentage": 0,
            "true_shooting_percentage": 0,
            "turnover_ratio": 0,
            "usage_percentage": 0,
            "player": {
                "id": 2937,
                "first_name": "Charles",
                "last_name": "Barkley",
                "position": "",
                "height": "6-6",
                "weight": "252",
                "jersey_number": "34",
                "college": "Auburn",
                "country": "USA",
                "draft_year": 1984,
                "draft_round": 1,
                "draft_number": 5,
                "team_id": 23
            },
            "team": {
                "id": 11,
                "conference": "West",
                "division": "Southwest",
                "city": "Houston",
                "name": "Rockets",
                "full_name": "Houston Rockets",
                "abbreviation": "HOU"
            },
            "game": {
                "id": 3524,
                "date": "1996-11-01",
                "season": 1996,
                "status": "Final",
                "period": 4,
                "time": " ",
                "postseason": false,
                "home_team_score": 96,
                "visitor_team_score": 85,
                "home_team_id": 11,
                "visitor_team_id": 26
            }
        },
        {
            "id": 43,
            "pie": 0.155,
            "pace": 90.79,
            "assist_percentage": 0.095,
            "assist_ratio": 20,
            "assist_to_turnover": 1,
            "defensive_rating": 96.9,
            "defensive_rebound_percentage": 0.13,
            "effective_field_goal_percentage": 0.875,
            "net_rating": 7.8,
            "offensive_rating": 104.8,
            "offensive_rebound_percentage": 0.038,
            "rebound_percentage": 0.097,
            "true_shooting_percentage": 0.955,
            "turnover_ratio": 20,
            "usage_percentage": 0.113,
            "player": {
                "id": 2880,
                "first_name": "Harvey",
                "last_name": "Grant",
                "position": "",
                "height": "6-9",
                "weight": "225",
                "jersey_number": "44",
                "college": "Oklahoma",
                "country": "USA",
                "draft_year": 1988,
                "draft_round": 1,
                "draft_number": 12,
                "team_id": 30
            },
            "team": {
                "id": 30,
                "conference": "East",
                "division": "Southeast",
                "city": "Washington",
                "name": "Wizards",
                "full_name": "Washington Wizards",
                "abbreviation": "WAS"
            },
            "game": {
                "id": 2722,
                "date": "1996-11-01",
                "season": 1996,
                "status": "Final",
                "period": 4,
                "time": " ",
                "postseason": false,
                "home_team_score": 92,
                "visitor_team_score": 96,
                "home_team_id": 22,
                "visitor_team_id": 30
            }
        },
        {
            "id": 44,
            "pie": 0.094,
            "pace": 89.85,
            "assist_percentage": 0.25,
            "assist_ratio": 21.4,
            "assist_to_turnover": 0.75,
            "defensive_rating": 106.8,
            "defensive_rebound_percentage": 0.098,
            "effective_field_goal_percentage": 0.5,
            "net_rating": 1.4,
            "offensive_rating": 108.1,
            "offensive_rebound_percentage": 0.152,
            "rebound_percentage": 0.119,
            "true_shooting_percentage": 0.581,
            "turnover_ratio": 28.6,
            "usage_percentage": 0.262,
            "player": {
                "id": 922,
                "first_name": "Juwan",
                "last_name": "Howard",
                "position": "",
                "height": "6-9",
                "weight": "250",
                "jersey_number": "5",
                "college": "Michigan",
                "country": "USA",
                "draft_year": 1994,
                "draft_round": 1,
                "draft_number": 5,
                "team_id": 30
            },
            "team": {
                "id": 30,
                "conference": "East",
                "division": "Southeast",
                "city": "Washington",
                "name": "Wizards",
                "full_name": "Washington Wizards",
                "abbreviation": "WAS"
            },
            "game": {
                "id": 2722,
                "date": "1996-11-01",
                "season": 1996,
                "status": "Final",
                "period": 4,
                "time": " ",
                "postseason": false,
                "home_team_score": 92,
                "visitor_team_score": 96,
                "home_team_id": 22,
                "visitor_team_id": 30
            }
        },
        {
            "id": 45,
            "pie": 0.046,
            "pace": 90.93,
            "assist_percentage": 0.125,
            "assist_ratio": 8,
            "assist_to_turnover": 0.67,
            "defensive_rating": 105.7,
            "defensive_rebound_percentage": 0.022,
            "effective_field_goal_percentage": 0.438,
            "net_rating": -7.1,
            "offensive_rating": 98.6,
            "offensive_rebound_percentage": 0,
            "rebound_percentage": 0.013,
            "true_shooting_percentage": 0.466,
            "turnover_ratio": 12,
            "usage_percentage": 0.284,
            "player": {
                "id": 847,
                "first_name": "Chris",
                "last_name": "Webber",
                "position": "",
                "height": "6-10",
                "weight": "245",
                "jersey_number": "4",
                "college": "Michigan",
                "country": "USA",
                "draft_year": 1993,
                "draft_round": 1,
                "draft_number": 1,
                "team_id": 26
            },
            "team": {
                "id": 30,
                "conference": "East",
                "division": "Southeast",
                "city": "Washington",
                "name": "Wizards",
                "full_name": "Washington Wizards",
                "abbreviation": "WAS"
            },
            "game": {
                "id": 2722,
                "date": "1996-11-01",
                "season": 1996,
                "status": "Final",
                "period": 4,
                "time": " ",
                "postseason": false,
                "home_team_score": 92,
                "visitor_team_score": 96,
                "home_team_id": 22,
                "visitor_team_id": 30
            }
        },
        {
            "id": 46,
            "pie": 0.06,
            "pace": 91.61,
            "assist_percentage": 0.053,
            "assist_ratio": 7.1,
            "assist_to_turnover": 1,
            "defensive_rating": 95.1,
            "defensive_rebound_percentage": 0.071,
            "effective_field_goal_percentage": 0.333,
            "net_rating": 9.9,
            "offensive_rating": 105,
            "offensive_rebound_percentage": 0.038,
            "rebound_percentage": 0.059,
            "true_shooting_percentage": 0.362,
            "turnover_ratio": 7.1,
            "usage_percentage": 0.191,
            "player": {
                "id": 820,
                "first_name": "Calbert",
                "last_name": "Cheaney",
                "position": "",
                "height": "6-7",
                "weight": "210",
                "jersey_number": "40",
                "college": "Indiana",
                "country": "USA",
                "draft_year": 1993,
                "draft_round": 1,
                "draft_number": 6,
                "team_id": 30
            },
            "team": {
                "id": 30,
                "conference": "East",
                "division": "Southeast",
                "city": "Washington",
                "name": "Wizards",
                "full_name": "Washington Wizards",
                "abbreviation": "WAS"
            },
            "game": {
                "id": 2722,
                "date": "1996-11-01",
                "season": 1996,
                "status": "Final",
                "period": 4,
                "time": " ",
                "postseason": false,
                "home_team_score": 92,
                "visitor_team_score": 96,
                "home_team_id": 22,
                "visitor_team_id": 30
            }
        }
    ],
    "meta": {
        "next_cursor": 46,
        "per_page": 25
    }
}